insta/__INIT__.py
insta_api/__INIT__.py
instafogging_api/__INIT__.py
instafogging_api-0.1.dist-info/METADATA
instafogging_api-0.1.dist-info/WHEEL
instafogging_api-0.1.dist-info/top_level.txt
instafogging_api-0.1.dist-info/RECORD
