Metadata-Version: 2.1
Name: instafogging_api
Version: 0.1
Summary: Description of your package
Home-page: https://github.com/allesx/insta
Author: xingpeidong
Author-email: xpd1437@126.com
License: MIT
Classifier: Programming Language :: Python :: 3
Requires-Dist: requests
